focs_gitea/__init__.py
focs_gitea/api_client.py
focs_gitea/configuration.py
focs_gitea/rest.py
focs_gitea/api/__init__.py
focs_gitea/api/activitypub_api.py
focs_gitea/api/admin_api.py
focs_gitea/api/issue_api.py
focs_gitea/api/miscellaneous_api.py
focs_gitea/api/notification_api.py
focs_gitea/api/organization_api.py
focs_gitea/api/package_api.py
focs_gitea/api/repository_api.py
focs_gitea/api/settings_api.py
focs_gitea/api/user_api.py
focs_gitea/models/__init__.py
focs_gitea/models/access_token.py
focs_gitea/models/action_variable.py
focs_gitea/models/activity.py
focs_gitea/models/activity_pub.py
focs_gitea/models/add_collaborator_option.py
focs_gitea/models/add_time_option.py
focs_gitea/models/annotated_tag.py
focs_gitea/models/annotated_tag_object.py
focs_gitea/models/api_error.py
focs_gitea/models/attachment.py
focs_gitea/models/badge.py
focs_gitea/models/branch.py
focs_gitea/models/branch_protection.py
focs_gitea/models/change_file_operation.py
focs_gitea/models/change_files_options.py
focs_gitea/models/changed_file.py
focs_gitea/models/combined_status.py
focs_gitea/models/comment.py
focs_gitea/models/commit.py
focs_gitea/models/commit_affected_files.py
focs_gitea/models/commit_date_options.py
focs_gitea/models/commit_meta.py
focs_gitea/models/commit_stats.py
focs_gitea/models/commit_status.py
focs_gitea/models/commit_status_state.py
focs_gitea/models/commit_user.py
focs_gitea/models/compare.py
focs_gitea/models/contents_response.py
focs_gitea/models/create_access_token_option.py
focs_gitea/models/create_branch_protection_option.py
focs_gitea/models/create_branch_repo_option.py
focs_gitea/models/create_email_option.py
focs_gitea/models/create_file_options.py
focs_gitea/models/create_fork_option.py
focs_gitea/models/create_gpg_key_option.py
focs_gitea/models/create_hook_option.py
focs_gitea/models/create_hook_option_config.py
focs_gitea/models/create_issue_comment_option.py
focs_gitea/models/create_issue_option.py
focs_gitea/models/create_key_option.py
focs_gitea-1.22.0.dist-info/METADATA
focs_gitea-1.22.0.dist-info/WHEEL
focs_gitea-1.22.0.dist-info/top_level.txt
focs_gitea-1.22.0.dist-info/RECORD
